bin/__init__.py
fenci/__init__.py
sougou_fenci-1.1.9.data/scripts/baidu_fenci
sougou_fenci-1.1.9.data/scripts/sougou_fenci
sougou_fenci-1.1.9.dist-info/METADATA
sougou_fenci-1.1.9.dist-info/WHEEL
sougou_fenci-1.1.9.dist-info/top_level.txt
sougou_fenci-1.1.9.dist-info/RECORD
